pwvalid/__init__.py
pwvalid-0.4.dist-info/METADATA
pwvalid-0.4.dist-info/WHEEL
pwvalid-0.4.dist-info/top_level.txt
pwvalid-0.4.dist-info/RECORD
