Metadata-Version: 2.1
Name: pwvalid
Version: 0.4
Summary: Validate Emails with ease
Home-page: UNKNOWN
Author: Vinay Chaudhary
License: UNKNOWN
Platform: UNKNOWN
